{"total":60,"pageSize":12,"pageCount":5,"data":[{"title":"奇怪的做幻灯片的方式又增加了","uid":"dea640c425e02970221e1f42331f9851","slug":"奇怪的做幻灯片的方式又增加了","date":"2022-01-26T09:45:23.000Z","updated":"2022-04-07T02:05:34.927Z","comments":true,"path":"api/articles/奇怪的做幻灯片的方式又增加了.json","cover":["https://murhyimgur.oss-cn-beijing.aliyuncs.com/website/student-849825_1920.jpg"],"text":"使用Markdown语法获得幻灯片演示效果，比较适用于总结类...","link":"","photos":[],"count_time":{"symbolsCount":702,"symbolsTime":"1 mins."},"categories":[{"name":"探索GitHub","slug":"探索GitHub","count":1,"path":"api/categories/探索GitHub.json"}],"tags":[{"name":"效率工具","slug":"效率工具","count":6,"path":"api/tags/效率工具.json"}],"author":{"name":"Murphy","slug":"blog-author","avatar":"https://murhyimgur.oss-cn-beijing.aliyuncs.com/img/aboutme.jpg","link":"/","description":"A Future Without Disappointment!","socials":{"github":"https://github.com/murphyhoucn","twitter":"","stackoverflow":"https://stackoverflow.com/users/18627097/murphy","wechat":"","qq":"","weibo":"","zhihu":"https://www.zhihu.com/people/CosmicDusty","csdn":"","juejin":"","customs":{"bilibili":{"icon":"/img/bilibili.png","link":"https://space.bilibili.com/294812632"}}}},"feature":false},{"title":"Windows端个人常用软件清单","uid":"1a41ee982f9a1261db38801fc66f5d05","slug":"Windows端个人常用软件清单","date":"2022-01-24T15:11:11.000Z","updated":"2022-04-07T02:02:45.913Z","comments":true,"path":"api/articles/Windows端个人常用软件清单.json","cover":["https://murhyimgur.oss-cn-beijing.aliyuncs.com/website/laptop-4947806_1920.jpg"],"text":"从小学开始就在使用电脑了，使用过的软件也有不少了了！使用电脑...","link":"","photos":[],"count_time":{"symbolsCount":"3k","symbolsTime":"3 mins."},"categories":[{"name":"工具利器","slug":"工具利器","count":8,"path":"api/categories/工具利器.json"}],"tags":[{"name":"效率工具","slug":"效率工具","count":6,"path":"api/tags/效率工具.json"}],"author":{"name":"Murphy","slug":"blog-author","avatar":"https://murhyimgur.oss-cn-beijing.aliyuncs.com/img/aboutme.jpg","link":"/","description":"A Future Without Disappointment!","socials":{"github":"https://github.com/murphyhoucn","twitter":"","stackoverflow":"https://stackoverflow.com/users/18627097/murphy","wechat":"","qq":"","weibo":"","zhihu":"https://www.zhihu.com/people/CosmicDusty","csdn":"","juejin":"","customs":{"bilibili":{"icon":"/img/bilibili.png","link":"https://space.bilibili.com/294812632"}}}},"feature":false},{"title":"Matlab","uid":"a33987437c8af57eae295fcc288dba2b","slug":"Matlab","date":"2022-01-16T10:36:18.000Z","updated":"2022-04-07T02:18:35.012Z","comments":true,"path":"api/articles/Matlab.json","cover":["https://murhyimgur.oss-cn-beijing.aliyuncs.com/website/matlab.jpg"],"text":"2020年因为需要做R老师的一个深度学习项目，根据论文的源代...","link":"","photos":[],"count_time":{"symbolsCount":708,"symbolsTime":"1 mins."},"categories":[{"name":"知识扩展","slug":"知识扩展","count":10,"path":"api/categories/知识扩展.json"}],"tags":[{"name":"Matlab","slug":"Matlab","count":1,"path":"api/tags/Matlab.json"}],"author":{"name":"Murphy","slug":"blog-author","avatar":"https://murhyimgur.oss-cn-beijing.aliyuncs.com/img/aboutme.jpg","link":"/","description":"A Future Without Disappointment!","socials":{"github":"https://github.com/murphyhoucn","twitter":"","stackoverflow":"https://stackoverflow.com/users/18627097/murphy","wechat":"","qq":"","weibo":"","zhihu":"https://www.zhihu.com/people/CosmicDusty","csdn":"","juejin":"","customs":{"bilibili":{"icon":"/img/bilibili.png","link":"https://space.bilibili.com/294812632"}}}},"feature":false},{"title":"2022读书记录","uid":"bd5642092347419b1be8e3b418364820","slug":"2022读书记录","date":"2021-12-31T16:00:10.000Z","updated":"2022-03-31T06:11:54.327Z","comments":true,"path":"api/articles/2022读书记录.json","cover":["https://murhyimgur.oss-cn-beijing.aliyuncs.com/website/Book2022.jpg"],"text":"2021年读书确实不少，特别是假期期间。2022年估计读书不...","link":"","photos":[],"count_time":{"symbolsCount":"6.4k","symbolsTime":"6 mins."},"categories":[{"name":"生活记录","slug":"生活记录","count":2,"path":"api/categories/生活记录.json"}],"tags":[{"name":"读书","slug":"读书","count":2,"path":"api/tags/读书.json"}],"author":{"name":"Murphy","slug":"blog-author","avatar":"https://murhyimgur.oss-cn-beijing.aliyuncs.com/img/aboutme.jpg","link":"/","description":"A Future Without Disappointment!","socials":{"github":"https://github.com/murphyhoucn","twitter":"","stackoverflow":"https://stackoverflow.com/users/18627097/murphy","wechat":"","qq":"","weibo":"","zhihu":"https://www.zhihu.com/people/CosmicDusty","csdn":"","juejin":"","customs":{"bilibili":{"icon":"/img/bilibili.png","link":"https://space.bilibili.com/294812632"}}}},"feature":false},{"title":"天文学合集笔记（一）","uid":"53d33b732925a7e605c56fab7d225420","slug":"天文学合集笔记（一）","date":"2021-12-27T13:48:03.000Z","updated":"2022-04-07T02:03:52.174Z","comments":true,"path":"api/articles/天文学合集笔记（一）.json","cover":["https://murhyimgur.oss-cn-beijing.aliyuncs.com/website/astronomy.jpg"],"text":"妈咪叔是我很喜欢的一个视频作者，每个视频讲的都很有深度！对天...","link":"","photos":[],"count_time":{"symbolsCount":"40k","symbolsTime":"37 mins."},"categories":[{"name":"天文","slug":"天文","count":5,"path":"api/categories/天文.json"}],"tags":[{"name":"妈咪说MommyTalk","slug":"妈咪说MommyTalk","count":2,"path":"api/tags/妈咪说MommyTalk.json"},{"name":"天文","slug":"天文","count":3,"path":"api/tags/天文.json"}],"author":{"name":"Murphy","slug":"blog-author","avatar":"https://murhyimgur.oss-cn-beijing.aliyuncs.com/img/aboutme.jpg","link":"/","description":"A Future Without Disappointment!","socials":{"github":"https://github.com/murphyhoucn","twitter":"","stackoverflow":"https://stackoverflow.com/users/18627097/murphy","wechat":"","qq":"","weibo":"","zhihu":"https://www.zhihu.com/people/CosmicDusty","csdn":"","juejin":"","customs":{"bilibili":{"icon":"/img/bilibili.png","link":"https://space.bilibili.com/294812632"}}}},"feature":false},{"title":"第一次深度学习尝试","uid":"b0401276265368b4880a947fdf74a498","slug":"第一次深度学习尝试","date":"2021-11-21T14:17:08.000Z","updated":"2022-04-07T02:17:30.489Z","comments":true,"path":"api/articles/第一次深度学习尝试.json","cover":["https://murhyimgur.oss-cn-beijing.aliyuncs.com/website/DEEPLEARN.jpg"],"text":"信息论小组作业，我主要负责代码部分。搭建起深度学习的环境，并...","link":"","photos":[],"count_time":{"symbolsCount":"33k","symbolsTime":"30 mins."},"categories":[{"name":"人工智能","slug":"人工智能","count":6,"path":"api/categories/人工智能.json"}],"tags":[{"name":"Python","slug":"Python","count":8,"path":"api/tags/Python.json"},{"name":"深度学习","slug":"深度学习","count":4,"path":"api/tags/深度学习.json"},{"name":"Linux","slug":"Linux","count":4,"path":"api/tags/Linux.json"},{"name":"PyTorch","slug":"PyTorch","count":1,"path":"api/tags/PyTorch.json"},{"name":"WSL","slug":"WSL","count":1,"path":"api/tags/WSL.json"}],"author":{"name":"Murphy","slug":"blog-author","avatar":"https://murhyimgur.oss-cn-beijing.aliyuncs.com/img/aboutme.jpg","link":"/","description":"A Future Without Disappointment!","socials":{"github":"https://github.com/murphyhoucn","twitter":"","stackoverflow":"https://stackoverflow.com/users/18627097/murphy","wechat":"","qq":"","weibo":"","zhihu":"https://www.zhihu.com/people/CosmicDusty","csdn":"","juejin":"","customs":{"bilibili":{"icon":"/img/bilibili.png","link":"https://space.bilibili.com/294812632"}}}},"feature":false},{"title":"ESP32CAM","uid":"32677db4598a540c2b555119b6c942b8","slug":"ESP32CAM","date":"2021-10-14T14:16:52.000Z","updated":"2022-03-31T06:11:37.747Z","comments":true,"path":"api/articles/ESP32CAM.json","cover":["https://murhyimgur.oss-cn-beijing.aliyuncs.com/website/esp32cam.jpg"],"text":"ESP32-CAM是安信可最新发布小尺寸的摄像头模组。该模块...","link":"","photos":[],"count_time":{"symbolsCount":700,"symbolsTime":"1 mins."},"categories":[{"name":"电子电路","slug":"电子电路","count":5,"path":"api/categories/电子电路.json"}],"tags":[{"name":"单片机","slug":"单片机","count":4,"path":"api/tags/单片机.json"}],"author":{"name":"Murphy","slug":"blog-author","avatar":"https://murhyimgur.oss-cn-beijing.aliyuncs.com/img/aboutme.jpg","link":"/","description":"A Future Without Disappointment!","socials":{"github":"https://github.com/murphyhoucn","twitter":"","stackoverflow":"https://stackoverflow.com/users/18627097/murphy","wechat":"","qq":"","weibo":"","zhihu":"https://www.zhihu.com/people/CosmicDusty","csdn":"","juejin":"","customs":{"bilibili":{"icon":"/img/bilibili.png","link":"https://space.bilibili.com/294812632"}}}},"feature":false},{"title":"ESP8266","uid":"d995faa79e16a475275a3eacab066b51","slug":"ESP8266","date":"2021-10-10T14:16:46.000Z","updated":"2022-03-31T06:11:37.394Z","comments":true,"path":"api/articles/ESP8266.json","cover":["https://murhyimgur.oss-cn-beijing.aliyuncs.com/website/esp8266.jpg"],"text":"ESP8266是一款物联网WiFi芯片，基于ESP8266可...","link":"","photos":[],"count_time":{"symbolsCount":"1.8k","symbolsTime":"2 mins."},"categories":[{"name":"电子电路","slug":"电子电路","count":5,"path":"api/categories/电子电路.json"}],"tags":[{"name":"单片机","slug":"单片机","count":4,"path":"api/tags/单片机.json"}],"author":{"name":"Murphy","slug":"blog-author","avatar":"https://murhyimgur.oss-cn-beijing.aliyuncs.com/img/aboutme.jpg","link":"/","description":"A Future Without Disappointment!","socials":{"github":"https://github.com/murphyhoucn","twitter":"","stackoverflow":"https://stackoverflow.com/users/18627097/murphy","wechat":"","qq":"","weibo":"","zhihu":"https://www.zhihu.com/people/CosmicDusty","csdn":"","juejin":"","customs":{"bilibili":{"icon":"/img/bilibili.png","link":"https://space.bilibili.com/294812632"}}}},"feature":false},{"title":"ESP32","uid":"963e9b0078ea5a0194618ba64cb70d01","slug":"ESP32","date":"2021-10-10T14:16:40.000Z","updated":"2022-03-31T06:11:38.200Z","comments":true,"path":"api/articles/ESP32.json","cover":["https://murhyimgur.oss-cn-beijing.aliyuncs.com/website/esp32.jpg"],"text":"ESP32模块是ESP8266的升级版本。除了Wi-Fi模块...","link":"","photos":[],"count_time":{"symbolsCount":115,"symbolsTime":"1 mins."},"categories":[{"name":"电子电路","slug":"电子电路","count":5,"path":"api/categories/电子电路.json"}],"tags":[{"name":"单片机","slug":"单片机","count":4,"path":"api/tags/单片机.json"}],"author":{"name":"Murphy","slug":"blog-author","avatar":"https://murhyimgur.oss-cn-beijing.aliyuncs.com/img/aboutme.jpg","link":"/","description":"A Future Without Disappointment!","socials":{"github":"https://github.com/murphyhoucn","twitter":"","stackoverflow":"https://stackoverflow.com/users/18627097/murphy","wechat":"","qq":"","weibo":"","zhihu":"https://www.zhihu.com/people/CosmicDusty","csdn":"","juejin":"","customs":{"bilibili":{"icon":"/img/bilibili.png","link":"https://space.bilibili.com/294812632"}}}},"feature":false},{"title":"ArduinoUno","uid":"0892a559d6416c59f72bd85df6acf532","slug":"ArduinoUno","date":"2021-10-10T14:16:31.000Z","updated":"2022-03-31T06:11:39.110Z","comments":true,"path":"api/articles/ArduinoUno.json","cover":["https://murhyimgur.oss-cn-beijing.aliyuncs.com/website/arduinouno.png"],"text":"Arduino是一款便捷灵活、方便上手的开源电子原型平台。包...","link":"","photos":[],"count_time":{"symbolsCount":304,"symbolsTime":"1 mins."},"categories":[{"name":"电子电路","slug":"电子电路","count":5,"path":"api/categories/电子电路.json"}],"tags":[{"name":"单片机","slug":"单片机","count":4,"path":"api/tags/单片机.json"}],"author":{"name":"Murphy","slug":"blog-author","avatar":"https://murhyimgur.oss-cn-beijing.aliyuncs.com/img/aboutme.jpg","link":"/","description":"A Future Without Disappointment!","socials":{"github":"https://github.com/murphyhoucn","twitter":"","stackoverflow":"https://stackoverflow.com/users/18627097/murphy","wechat":"","qq":"","weibo":"","zhihu":"https://www.zhihu.com/people/CosmicDusty","csdn":"","juejin":"","customs":{"bilibili":{"icon":"/img/bilibili.png","link":"https://space.bilibili.com/294812632"}}}},"feature":false},{"title":"庆国庆的微信头像生成","uid":"5e0e48af22772b0c004b4ff4968bed90","slug":"庆国庆的微信头像生成","date":"2021-09-30T13:39:48.000Z","updated":"2022-03-31T06:11:48.753Z","comments":true,"path":"api/articles/庆国庆的微信头像生成.json","cover":["https://murhyimgur.oss-cn-beijing.aliyuncs.com/website/portrait.jpg"],"text":"举国同庆盛世中华！2021年的国庆节即将到来，国庆的氛围也逐...","link":"","photos":[],"count_time":{"symbolsCount":"1.9k","symbolsTime":"2 mins."},"categories":[{"name":"想法实现","slug":"想法实现","count":5,"path":"api/categories/想法实现.json"}],"tags":[{"name":"Python","slug":"Python","count":8,"path":"api/tags/Python.json"},{"name":"PIL","slug":"PIL","count":2,"path":"api/tags/PIL.json"}],"author":{"name":"Murphy","slug":"blog-author","avatar":"https://murhyimgur.oss-cn-beijing.aliyuncs.com/img/aboutme.jpg","link":"/","description":"A Future Without Disappointment!","socials":{"github":"https://github.com/murphyhoucn","twitter":"","stackoverflow":"https://stackoverflow.com/users/18627097/murphy","wechat":"","qq":"","weibo":"","zhihu":"https://www.zhihu.com/people/CosmicDusty","csdn":"","juejin":"","customs":{"bilibili":{"icon":"/img/bilibili.png","link":"https://space.bilibili.com/294812632"}}}},"feature":false},{"title":"Git常用命令与使用","uid":"c536060a2511bbae5ad356202826fe9e","slug":"Git常用命令与使用","date":"2021-09-20T14:16:23.000Z","updated":"2022-04-07T02:18:36.635Z","comments":true,"path":"api/articles/Git常用命令与使用.json","cover":["https://murhyimgur.oss-cn-beijing.aliyuncs.com/website/Gitbg.jpg"],"text":"Git 是一个开源的分布式版本控制系统，用于敏捷高效地处理任...","link":"","photos":[],"count_time":{"symbolsCount":"14k","symbolsTime":"13 mins."},"categories":[{"name":"工具利器","slug":"工具利器","count":8,"path":"api/categories/工具利器.json"}],"tags":[{"name":"效率工具","slug":"效率工具","count":6,"path":"api/tags/效率工具.json"}],"author":{"name":"Murphy","slug":"blog-author","avatar":"https://murhyimgur.oss-cn-beijing.aliyuncs.com/img/aboutme.jpg","link":"/","description":"A Future Without Disappointment!","socials":{"github":"https://github.com/murphyhoucn","twitter":"","stackoverflow":"https://stackoverflow.com/users/18627097/murphy","wechat":"","qq":"","weibo":"","zhihu":"https://www.zhihu.com/people/CosmicDusty","csdn":"","juejin":"","customs":{"bilibili":{"icon":"/img/bilibili.png","link":"https://space.bilibili.com/294812632"}}}},"feature":false}]}