{"name":"运营商","slug":"运营商","count":1,"postlist":[{"title":"中国运营商移动通讯标准","uid":"6ec7ae9bb3d64ba848acce4c6c29abba","slug":"中国运营商移动通讯标准","date":"2022-02-24T13:17:19.000Z","updated":"2022-06-06T03:15:04.000Z","comments":true,"path":"api/articles/中国运营商移动通讯标准.json","keywords":"Blog","cover":["https://murhyimgur.oss-cn-beijing.aliyuncs.com/website/cell-tower-5207588_1920.jpg"],"text":"提供网络服务的供应商，如华为、中兴、诺基亚、爱立信等这些通信...","link":"","photos":[],"count_time":{"symbolsCount":"3.4k","symbolsTime":"3 mins."},"categories":[{"name":"知识扩展","slug":"知识扩展","count":9,"path":"api/categories/知识扩展.json"}],"tags":[{"name":"通信技术","slug":"通信技术","count":1,"path":"api/tags/通信技术.json"},{"name":"运营商","slug":"运营商","count":1,"path":"api/tags/运营商.json"}],"author":{"name":"Murphy","slug":"blog-author","avatar":"https://murhyimgur.oss-cn-beijing.aliyuncs.com/img/aboutme.jpg","link":"/","description":"A Future Without Disappointment!","socials":{"github":"https://github.com/murphyhoucn","twitter":"","stackoverflow":"https://stackoverflow.com/users/18627097/murphy","wechat":"","qq":"","weibo":"","zhihu":"https://www.zhihu.com/people/CosmicDusty","csdn":"","juejin":"","customs":{"bilibili":{"icon":"/img/bilibili.png","link":"https://space.bilibili.com/294812632"}}}},"feature":false}]}